terrakio_admin_api/__init__.py
terrakio_admin_api_beta-0.4.98.dist-info/METADATA
terrakio_admin_api_beta-0.4.98.dist-info/WHEEL
terrakio_admin_api_beta-0.4.98.dist-info/RECORD
