Metadata-Version: 2.4
Name: terrakio-admin-api-beta
Version: 0.4.98
Summary: Admin version of the terrakio-python-api
Requires-Python: >=3.11
Requires-Dist: terrakio-core==0.4.98
